{
  "parent": "minecraft:recipes/root",
  "criteria": {
    "has_the_recipe": {
      "conditions": {
        "recipe": "minecraft:charged_claw"
      },
      "trigger": "minecraft:recipe_unlocked"
    },
    "lightning_rod": {
      "conditions": {
        "items": [
          {
            "items": "minecraft:lightning_rod"
          }
        ]
      },
      "trigger": "minecraft:inventory_changed"
    },
    "mythril": {
      "conditions": {
        "items": [
          {
            "items": "bruhmod:mythril"
          }
        ]
      },
      "trigger": "minecraft:inventory_changed"
    },
    "volatile_claw": {
      "conditions": {
        "items": [
          {
            "items": "bruhmod:volatile_claw"
          }
        ]
      },
      "trigger": "minecraft:inventory_changed"
    }
  },
  "requirements": [
    [
      "has_the_recipe",
      "volatile_claw",
      "mythril",
      "lightning_rod"
    ]
  ],
  "rewards": {
    "recipes": [
      "minecraft:charged_claw"
    ]
  }
}